{
    "version": 8,
    "cmakeMinimumRequired": {
      "major": 3,
      "minor": 29,
      "patch": 0
    },
    "configurePresets": [
      {
        "name": "default",
        "binaryDir": "build",
        "toolchainFile": "cmake/cosmocc.cmake",
        "cacheVariables": {
          "CMAKE_BUILD_TYPE": "Debug"
        }
      },
      {
        "name": "release",
        "inherits": ["default"],
        "binaryDir": "build/release",
        "cacheVariables": {
          "CMAKE_BUILD_TYPE": "Release",
          "BUILD_TESTING": false
        }
      }
    ],
    "buildPresets": [
        { "name": "default", "configurePreset": "default", "configuration": "Debug" },
        { "name": "release", "configurePreset": "release", "configuration": "Release" }
    ],
    "workflowPresets": [
        {
            "name": "default",
            "steps": [
                { "type": "configure", "name": "default" },
                { "type": "build", "name": "default" }
            ]
        },
        {
            "name": "release",
            "steps": [
                { "type": "configure", "name": "release" },
                { "type": "build", "name": "release" }
            ]
        }
    ]
  }